django_seo2-1.0.1.dist-info/DESCRIPTION.rst
django_seo2-1.0.1.dist-info/METADATA
django_seo2-1.0.1.dist-info/metadata.json
django_seo2-1.0.1.dist-info/RECORD
django_seo2-1.0.1.dist-info/top_level.txt
django_seo2-1.0.1.dist-info/WHEEL
djangoseo/__init__.py
djangoseo/admin.py
djangoseo/apps.py
djangoseo/backends.py
djangoseo/base.py
djangoseo/default.py
djangoseo/fields.py
djangoseo/models.py
djangoseo/options.py
djangoseo/seo.py
djangoseo/systemviews.py
djangoseo/utils.py
djangoseo/management/__init__.py
djangoseo/management/commands/__init__.py
djangoseo/management/commands/populate_metadata.py
djangoseo/templatetags/__init__.py
djangoseo/templatetags/seo.py
